opentsdb2py/__init__.py
opentsdb2py/client.py
opentsdb2py/query.py
opentsdb2py/request.py
opentsdb2py/utils.py
opentsdb2py-0.1.3.dist-info/METADATA
opentsdb2py-0.1.3.dist-info/WHEEL
opentsdb2py-0.1.3.dist-info/licenses/LICENSE
opentsdb2py-0.1.3.dist-info/RECORD
